MANIFEST.in
setup.py
TogetherVideo.egg-info/PKG-INFO
TogetherVideo.egg-info/SOURCES.txt
TogetherVideo.egg-info/dependency_links.txt
TogetherVideo.egg-info/requires.txt
TogetherVideo.egg-info/top_level.txt
tv/__init__.py
tv/models.py
tv/routes.py
tv/auth/__init__.py
tv/auth/openid.py