Metadata-Version: 1.0
Name: TogetherVideo
Version: 0.1.0
Summary: An application that lets multiple people watch HTML5 video together.
Home-page: https://github.com/together-video
Author: Ryan Lane
Author-email: ryan@ryandlane.com
License: apache2
Platform: UNKNOWN
